[
    {
        "%vlocity_namespace%__DomainObjectAPIName__c": "json",
        "%vlocity_namespace%__DomainObjectCreationOrder__c": 0,
        "%vlocity_namespace%__DomainObjectFieldAPIName__c": "ServicePlan",
        "%vlocity_namespace%__FilterGroup__c": 0,
        "%vlocity_namespace%__FilterOperator__c": "=",
        "%vlocity_namespace%__FilterValue__c": "Id",
        "%vlocity_namespace%__InterfaceFieldAPIName__c": "Id",
        "%vlocity_namespace%__InterfaceObjectLookupOrder__c": 1,
        "%vlocity_namespace%__InterfaceObjectName__c": "%vlocity_namespace%__BenefitCaseServicePlan__c",
        "%vlocity_namespace%__IsDisabled__c": false,
        "%vlocity_namespace%__IsRequiredForUpsert__c": false,
        "%vlocity_namespace%__MapId__c": "CW-GetServicePlanObjectivesServicesCustom9972",
        "%vlocity_namespace%__UpsertKey__c": false,
        "CurrencyIsoCode": "USD",
        "Name": "CW-GetServicePlanObjectivesServices",
        "VlocityDataPackType": "SObject",
        "VlocityRecordSObjectType": "%vlocity_namespace%__DRMapItem__c"
    },
    {
        "%vlocity_namespace%__DomainObjectAPIName__c": "json",
        "%vlocity_namespace%__DomainObjectCreationOrder__c": 0,
        "%vlocity_namespace%__DomainObjectFieldAPIName__c": "Outcome",
        "%vlocity_namespace%__FilterGroup__c": 0,
        "%vlocity_namespace%__FilterOperator__c": "=",
        "%vlocity_namespace%__FilterValue__c": "ServicePlan:Id",
        "%vlocity_namespace%__InterfaceFieldAPIName__c": "%vlocity_namespace%__ServicePlanId__c",
        "%vlocity_namespace%__InterfaceObjectLookupOrder__c": 2,
        "%vlocity_namespace%__InterfaceObjectName__c": "%vlocity_namespace%__ServicePlanOutcome__c",
        "%vlocity_namespace%__IsDisabled__c": false,
        "%vlocity_namespace%__IsRequiredForUpsert__c": false,
        "%vlocity_namespace%__MapId__c": "CW-GetServicePlanObjectivesServicesCustom3925",
        "%vlocity_namespace%__UpsertKey__c": false,
        "CurrencyIsoCode": "USD",
        "Name": "CW-GetServicePlanObjectivesServices",
        "VlocityDataPackType": "SObject",
        "VlocityRecordSObjectType": "%vlocity_namespace%__DRMapItem__c"
    },
    {
        "%vlocity_namespace%__DomainObjectAPIName__c": "json",
        "%vlocity_namespace%__DomainObjectCreationOrder__c": 0,
        "%vlocity_namespace%__DomainObjectFieldAPIName__c": "Objective",
        "%vlocity_namespace%__FilterGroup__c": 0,
        "%vlocity_namespace%__FilterOperator__c": "=",
        "%vlocity_namespace%__FilterValue__c": "Outcome:Id",
        "%vlocity_namespace%__InterfaceFieldAPIName__c": "Outcome__c",
        "%vlocity_namespace%__InterfaceObjectLookupOrder__c": 3,
        "%vlocity_namespace%__InterfaceObjectName__c": "Plan_Objective__c",
        "%vlocity_namespace%__IsDisabled__c": false,
        "%vlocity_namespace%__IsRequiredForUpsert__c": false,
        "%vlocity_namespace%__MapId__c": "CW-GetServicePlanObjectivesServicesCustom9755",
        "%vlocity_namespace%__UpsertKey__c": false,
        "CurrencyIsoCode": "USD",
        "Name": "CW-GetServicePlanObjectivesServices",
        "VlocityDataPackType": "SObject",
        "VlocityRecordSObjectType": "%vlocity_namespace%__DRMapItem__c"
    },
    {
        "%vlocity_namespace%__DomainObjectAPIName__c": "json",
        "%vlocity_namespace%__DomainObjectCreationOrder__c": 0,
        "%vlocity_namespace%__DomainObjectFieldAPIName__c": "Services",
        "%vlocity_namespace%__FilterGroup__c": 0,
        "%vlocity_namespace%__FilterOperator__c": "=",
        "%vlocity_namespace%__FilterValue__c": "ServicePlan:Id",
        "%vlocity_namespace%__InterfaceFieldAPIName__c": "%vlocity_namespace%__ServicePlanId__c",
        "%vlocity_namespace%__InterfaceObjectLookupOrder__c": 4,
        "%vlocity_namespace%__InterfaceObjectName__c": "%vlocity_namespace%__ServicePlanServicesProducts__c",
        "%vlocity_namespace%__IsDisabled__c": false,
        "%vlocity_namespace%__IsRequiredForUpsert__c": false,
        "%vlocity_namespace%__MapId__c": "CW-GetServicePlanObjectivesServicesCustom242",
        "%vlocity_namespace%__UpsertKey__c": false,
        "CurrencyIsoCode": "USD",
        "Name": "CW-GetServicePlanObjectivesServices",
        "VlocityDataPackType": "SObject",
        "VlocityRecordSObjectType": "%vlocity_namespace%__DRMapItem__c"
    },
    {
        "%vlocity_namespace%__DomainObjectAPIName__c": "json",
        "%vlocity_namespace%__DomainObjectCreationOrder__c": 1,
        "%vlocity_namespace%__DomainObjectFieldAPIName__c": "Objective:ObjectiveId",
        "%vlocity_namespace%__InterfaceFieldAPIName__c": "Objective:Id",
        "%vlocity_namespace%__IsDisabled__c": false,
        "%vlocity_namespace%__IsRequiredForUpsert__c": false,
        "%vlocity_namespace%__MapId__c": "CW-GetServicePlanObjectivesServicesCustom9670",
        "%vlocity_namespace%__UpsertKey__c": false,
        "CurrencyIsoCode": "USD",
        "Name": "CW-GetServicePlanObjectivesServices",
        "VlocityDataPackType": "SObject",
        "VlocityRecordSObjectType": "%vlocity_namespace%__DRMapItem__c"
    },
    {
        "%vlocity_namespace%__DomainObjectAPIName__c": "json",
        "%vlocity_namespace%__DomainObjectCreationOrder__c": 1,
        "%vlocity_namespace%__DomainObjectFieldAPIName__c": "Objective:ObjectiveName",
        "%vlocity_namespace%__InterfaceFieldAPIName__c": "Objective:Name",
        "%vlocity_namespace%__IsDisabled__c": false,
        "%vlocity_namespace%__IsRequiredForUpsert__c": false,
        "%vlocity_namespace%__MapId__c": "CW-GetServicePlanObjectivesServicesCustom2995",
        "%vlocity_namespace%__UpsertKey__c": false,
        "CurrencyIsoCode": "USD",
        "Name": "CW-GetServicePlanObjectivesServices",
        "VlocityDataPackType": "SObject",
        "VlocityRecordSObjectType": "%vlocity_namespace%__DRMapItem__c"
    },
    {
        "%vlocity_namespace%__DomainObjectAPIName__c": "json",
        "%vlocity_namespace%__DomainObjectCreationOrder__c": 1,
        "%vlocity_namespace%__DomainObjectFieldAPIName__c": "Objective:Objective_Description",
        "%vlocity_namespace%__InterfaceFieldAPIName__c": "Objective:Objective_Description__c",
        "%vlocity_namespace%__IsDisabled__c": false,
        "%vlocity_namespace%__IsRequiredForUpsert__c": false,
        "%vlocity_namespace%__MapId__c": "CW-GetServicePlanObjectivesServicesCustom2869",
        "%vlocity_namespace%__UpsertKey__c": false,
        "CurrencyIsoCode": "USD",
        "Name": "CW-GetServicePlanObjectivesServices",
        "VlocityDataPackType": "SObject",
        "VlocityRecordSObjectType": "%vlocity_namespace%__DRMapItem__c"
    },
    {
        "%vlocity_namespace%__DomainObjectAPIName__c": "json",
        "%vlocity_namespace%__DomainObjectCreationOrder__c": 1,
        "%vlocity_namespace%__DomainObjectFieldAPIName__c": "Objective:PartyName",
        "%vlocity_namespace%__InterfaceFieldAPIName__c": "Objective:Outcome__r.Party__r.Name",
        "%vlocity_namespace%__IsDisabled__c": false,
        "%vlocity_namespace%__IsRequiredForUpsert__c": false,
        "%vlocity_namespace%__MapId__c": "CW-GetServicePlanObjectivesServicesCustom3718",
        "%vlocity_namespace%__UpsertKey__c": false,
        "CurrencyIsoCode": "USD",
        "Name": "CW-GetServicePlanObjectivesServices",
        "VlocityDataPackType": "SObject",
        "VlocityRecordSObjectType": "%vlocity_namespace%__DRMapItem__c"
    },
    {
        "%vlocity_namespace%__DomainObjectAPIName__c": "json",
        "%vlocity_namespace%__DomainObjectCreationOrder__c": 1,
        "%vlocity_namespace%__DomainObjectFieldAPIName__c": "Objective:Progress",
        "%vlocity_namespace%__InterfaceFieldAPIName__c": "Objective:Progress__c",
        "%vlocity_namespace%__IsDisabled__c": false,
        "%vlocity_namespace%__IsRequiredForUpsert__c": false,
        "%vlocity_namespace%__MapId__c": "CW-GetServicePlanObjectivesServicesCustom5886",
        "%vlocity_namespace%__UpsertKey__c": false,
        "CurrencyIsoCode": "USD",
        "Name": "CW-GetServicePlanObjectivesServices",
        "VlocityDataPackType": "SObject",
        "VlocityRecordSObjectType": "%vlocity_namespace%__DRMapItem__c"
    },
    {
        "%vlocity_namespace%__DomainObjectAPIName__c": "json",
        "%vlocity_namespace%__DomainObjectCreationOrder__c": 1,
        "%vlocity_namespace%__DomainObjectFieldAPIName__c": "Objective:ServicePlanOutcome",
        "%vlocity_namespace%__InterfaceFieldAPIName__c": "Objective:Outcome__r.Name",
        "%vlocity_namespace%__IsDisabled__c": false,
        "%vlocity_namespace%__IsRequiredForUpsert__c": false,
        "%vlocity_namespace%__MapId__c": "CW-GetServicePlanObjectivesServicesCustom5678",
        "%vlocity_namespace%__UpsertKey__c": false,
        "CurrencyIsoCode": "USD",
        "Name": "CW-GetServicePlanObjectivesServices",
        "VlocityDataPackType": "SObject",
        "VlocityRecordSObjectType": "%vlocity_namespace%__DRMapItem__c"
    },
    {
        "%vlocity_namespace%__DomainObjectAPIName__c": "json",
        "%vlocity_namespace%__DomainObjectCreationOrder__c": 1,
        "%vlocity_namespace%__DomainObjectFieldAPIName__c": "Objective:Start_Date",
        "%vlocity_namespace%__InterfaceFieldAPIName__c": "Objective:Start_Date__c",
        "%vlocity_namespace%__IsDisabled__c": false,
        "%vlocity_namespace%__IsRequiredForUpsert__c": false,
        "%vlocity_namespace%__MapId__c": "CW-GetServicePlanObjectivesServicesCustom2280",
        "%vlocity_namespace%__UpsertKey__c": false,
        "CurrencyIsoCode": "USD",
        "Name": "CW-GetServicePlanObjectivesServices",
        "VlocityDataPackType": "SObject",
        "VlocityRecordSObjectType": "%vlocity_namespace%__DRMapItem__c"
    },
    {
        "%vlocity_namespace%__DomainObjectAPIName__c": "json",
        "%vlocity_namespace%__DomainObjectCreationOrder__c": 1,
        "%vlocity_namespace%__DomainObjectFieldAPIName__c": "Objective:Status",
        "%vlocity_namespace%__InterfaceFieldAPIName__c": "Objective:Status__c",
        "%vlocity_namespace%__IsDisabled__c": false,
        "%vlocity_namespace%__IsRequiredForUpsert__c": false,
        "%vlocity_namespace%__MapId__c": "CW-GetServicePlanObjectivesServicesCustom8602",
        "%vlocity_namespace%__UpsertKey__c": false,
        "CurrencyIsoCode": "USD",
        "Name": "CW-GetServicePlanObjectivesServices",
        "VlocityDataPackType": "SObject",
        "VlocityRecordSObjectType": "%vlocity_namespace%__DRMapItem__c"
    },
    {
        "%vlocity_namespace%__DomainObjectAPIName__c": "json",
        "%vlocity_namespace%__DomainObjectCreationOrder__c": 1,
        "%vlocity_namespace%__DomainObjectFieldAPIName__c": "Objective:Target_Completion_Date",
        "%vlocity_namespace%__InterfaceFieldAPIName__c": "Objective:Target_Completion_Date__c",
        "%vlocity_namespace%__IsDisabled__c": false,
        "%vlocity_namespace%__IsRequiredForUpsert__c": false,
        "%vlocity_namespace%__MapId__c": "CW-GetServicePlanObjectivesServicesCustom2084",
        "%vlocity_namespace%__UpsertKey__c": false,
        "CurrencyIsoCode": "USD",
        "Name": "CW-GetServicePlanObjectivesServices",
        "VlocityDataPackType": "SObject",
        "VlocityRecordSObjectType": "%vlocity_namespace%__DRMapItem__c"
    },
    {
        "%vlocity_namespace%__DomainObjectAPIName__c": "json",
        "%vlocity_namespace%__DomainObjectCreationOrder__c": 1,
        "%vlocity_namespace%__DomainObjectFieldAPIName__c": "Services:PartyName",
        "%vlocity_namespace%__InterfaceFieldAPIName__c": "Services:Outcome__r.Party__r.Name",
        "%vlocity_namespace%__IsDisabled__c": false,
        "%vlocity_namespace%__IsRequiredForUpsert__c": false,
        "%vlocity_namespace%__MapId__c": "CW-GetServicePlanObjectivesServicesCustom5773",
        "%vlocity_namespace%__UpsertKey__c": false,
        "CurrencyIsoCode": "USD",
        "Name": "CW-GetServicePlanObjectivesServices",
        "VlocityDataPackType": "SObject",
        "VlocityRecordSObjectType": "%vlocity_namespace%__DRMapItem__c"
    },
    {
        "%vlocity_namespace%__DomainObjectAPIName__c": "json",
        "%vlocity_namespace%__DomainObjectCreationOrder__c": 1,
        "%vlocity_namespace%__DomainObjectFieldAPIName__c": "Services:Product",
        "%vlocity_namespace%__InterfaceFieldAPIName__c": "Services:%vlocity_namespace%__Product__r.Name",
        "%vlocity_namespace%__IsDisabled__c": false,
        "%vlocity_namespace%__IsRequiredForUpsert__c": false,
        "%vlocity_namespace%__MapId__c": "CW-GetServicePlanObjectivesServicesCustom722",
        "%vlocity_namespace%__UpsertKey__c": false,
        "CurrencyIsoCode": "USD",
        "Name": "CW-GetServicePlanObjectivesServices",
        "VlocityDataPackType": "SObject",
        "VlocityRecordSObjectType": "%vlocity_namespace%__DRMapItem__c"
    },
    {
        "%vlocity_namespace%__DomainObjectAPIName__c": "json",
        "%vlocity_namespace%__DomainObjectCreationOrder__c": 1,
        "%vlocity_namespace%__DomainObjectFieldAPIName__c": "Services:Provider",
        "%vlocity_namespace%__InterfaceFieldAPIName__c": "Services:Provider__r.Name",
        "%vlocity_namespace%__IsDisabled__c": false,
        "%vlocity_namespace%__IsRequiredForUpsert__c": false,
        "%vlocity_namespace%__MapId__c": "CW-GetServicePlanObjectivesServicesCustom4409",
        "%vlocity_namespace%__UpsertKey__c": false,
        "CurrencyIsoCode": "USD",
        "Name": "CW-GetServicePlanObjectivesServices",
        "VlocityDataPackType": "SObject",
        "VlocityRecordSObjectType": "%vlocity_namespace%__DRMapItem__c"
    },
    {
        "%vlocity_namespace%__DomainObjectAPIName__c": "json",
        "%vlocity_namespace%__DomainObjectCreationOrder__c": 1,
        "%vlocity_namespace%__DomainObjectFieldAPIName__c": "Services:Quantity",
        "%vlocity_namespace%__InterfaceFieldAPIName__c": "Services:%vlocity_namespace%__Quantity__c",
        "%vlocity_namespace%__IsDisabled__c": false,
        "%vlocity_namespace%__IsRequiredForUpsert__c": false,
        "%vlocity_namespace%__MapId__c": "CW-GetServicePlanObjectivesServicesCustom7969",
        "%vlocity_namespace%__UpsertKey__c": false,
        "CurrencyIsoCode": "USD",
        "Name": "CW-GetServicePlanObjectivesServices",
        "VlocityDataPackType": "SObject",
        "VlocityRecordSObjectType": "%vlocity_namespace%__DRMapItem__c"
    },
    {
        "%vlocity_namespace%__DomainObjectAPIName__c": "json",
        "%vlocity_namespace%__DomainObjectCreationOrder__c": 1,
        "%vlocity_namespace%__DomainObjectFieldAPIName__c": "Services:ServicesId",
        "%vlocity_namespace%__InterfaceFieldAPIName__c": "Services:Id",
        "%vlocity_namespace%__IsDisabled__c": false,
        "%vlocity_namespace%__IsRequiredForUpsert__c": false,
        "%vlocity_namespace%__MapId__c": "CW-GetServicePlanObjectivesServicesCustom7428",
        "%vlocity_namespace%__UpsertKey__c": false,
        "CurrencyIsoCode": "USD",
        "Name": "CW-GetServicePlanObjectivesServices",
        "VlocityDataPackType": "SObject",
        "VlocityRecordSObjectType": "%vlocity_namespace%__DRMapItem__c"
    }
]