{
    "%vlocity_namespace%__Active__c": true,
    "%vlocity_namespace%__OmniScriptId__c": {
        "Name": "Mandatory Reporter",
        "VlocityDataPackType": "VlocityMatchingKeyObject",
        "VlocityMatchingRecordSourceKey": "%vlocity_namespace%__OmniScript__c/CCWIS/Mandatory Reporter/English",
        "VlocityRecordSObjectType": "%vlocity_namespace%__OmniScript__c"
    },
    "%vlocity_namespace%__ParentElementId__c": {
        "%vlocity_namespace%__OmniScriptId__c": {
            "Name": "Mandatory Reporter",
            "VlocityDataPackType": "VlocityMatchingKeyObject",
            "VlocityMatchingRecordSourceKey": "%vlocity_namespace%__OmniScript__c/CCWIS/Mandatory Reporter/English",
            "VlocityRecordSObjectType": "%vlocity_namespace%__OmniScript__c"
        },
        "Name": "OtherAdult",
        "VlocityDataPackType": "VlocityMatchingKeyObject",
        "VlocityMatchingRecordSourceKey": "%vlocity_namespace%__Element__c/%vlocity_namespace%__OmniScript__c/CCWIS/Mandatory Reporter/English/OtherAdult",
        "VlocityRecordSObjectType": "%vlocity_namespace%__Element__c"
    },
    "%vlocity_namespace%__ParentElementName__c": "OtherAdult",
    "%vlocity_namespace%__ParentElementType__c": "Edit Block",
    "%vlocity_namespace%__PropertySet__c": {
        "HTMLTemplateId": "",
        "accessibleInFutureSteps": false,
        "conditionType": "Hide if False",
        "controlWidth": 12,
        "controllingField": {
            "element": "",
            "source": "",
            "type": ""
        },
        "defaultValue": null,
        "disOnTplt": false,
        "help": false,
        "helpText": "",
        "hide": false,
        "inputWidth": 12,
        "label": "Relationship to Household",
        "optionSource": {
            "source": "",
            "type": ""
        },
        "options": [
            {
                "name": "Parent",
                "value": "Parent"
            },
            {
                "name": "Boyfriend",
                "value": "Boyfriend"
            },
            {
                "name": "Girlfriend",
                "value": "Girlfriend"
            },
            {
                "name": "Spouse",
                "value": "Spouse"
            },
            {
                "name": "Grandparent",
                "value": "Grandparent"
            },
            {
                "name": "Sibling",
                "value": "Sibling"
            },
            {
                "name": "Foster child",
                "value": "Foster child"
            },
            {
                "name": "Member",
                "value": "Other Household Member"
            }
        ],
        "readOnly": false,
        "repeat": false,
        "repeatClone": false,
        "repeatLimit": null,
        "required": false,
        "show": null,
        "showInputWidth": false
    },
    "%vlocity_namespace%__ReusableOmniScript__c": true,
    "%vlocity_namespace%__Type__c": "Select",
    "CurrencyIsoCode": "USD",
    "Name": "OtherAdultRelationship",
    "VlocityDataPackType": "SObject",
    "VlocityRecordSObjectType": "%vlocity_namespace%__Element__c",
    "VlocityRecordSourceKey": "%vlocity_namespace%__Element__c/%vlocity_namespace%__OmniScript__c/CCWIS/Mandatory Reporter/English/OtherAdultRelationship"
}