[
    {
        "%vlocity_namespace%__DomainObjectAPIName__c": "json",
        "%vlocity_namespace%__DomainObjectCreationOrder__c": 0,
        "%vlocity_namespace%__DomainObjectFieldAPIName__c": "Participant",
        "%vlocity_namespace%__FilterGroup__c": 0,
        "%vlocity_namespace%__FilterOperator__c": "=",
        "%vlocity_namespace%__FilterValue__c": "SocialSecurityNumber",
        "%vlocity_namespace%__InterfaceFieldAPIName__c": "%vlocity_namespace%__SocialSecurityNumber__c",
        "%vlocity_namespace%__InterfaceObjectLookupOrder__c": 1,
        "%vlocity_namespace%__InterfaceObjectName__c": "Contact",
        "%vlocity_namespace%__IsDisabled__c": false,
        "%vlocity_namespace%__IsRequiredForUpsert__c": false,
        "%vlocity_namespace%__MapId__c": "ParticipantSearchCustom7188",
        "%vlocity_namespace%__UpsertKey__c": false,
        "CurrencyIsoCode": "USD",
        "Name": "ParticipantSearch",
        "VlocityDataPackType": "SObject",
        "VlocityRecordSObjectType": "%vlocity_namespace%__DRMapItem__c"
    },
    {
        "%vlocity_namespace%__DomainObjectAPIName__c": "json",
        "%vlocity_namespace%__DomainObjectCreationOrder__c": 0,
        "%vlocity_namespace%__DomainObjectFieldAPIName__c": "Participant",
        "%vlocity_namespace%__FilterGroup__c": 1,
        "%vlocity_namespace%__FilterOperator__c": "LIKE",
        "%vlocity_namespace%__FilterValue__c": "LastName",
        "%vlocity_namespace%__InterfaceFieldAPIName__c": "LastName",
        "%vlocity_namespace%__InterfaceObjectLookupOrder__c": 1,
        "%vlocity_namespace%__InterfaceObjectName__c": "Contact",
        "%vlocity_namespace%__IsDisabled__c": false,
        "%vlocity_namespace%__IsRequiredForUpsert__c": false,
        "%vlocity_namespace%__MapId__c": "ParticipantSearchCustom5374",
        "%vlocity_namespace%__UpsertKey__c": false,
        "CurrencyIsoCode": "USD",
        "Name": "ParticipantSearch",
        "VlocityDataPackType": "SObject",
        "VlocityRecordSObjectType": "%vlocity_namespace%__DRMapItem__c"
    },
    {
        "%vlocity_namespace%__DomainObjectAPIName__c": "json",
        "%vlocity_namespace%__DomainObjectCreationOrder__c": 0,
        "%vlocity_namespace%__DomainObjectFieldAPIName__c": "Participant",
        "%vlocity_namespace%__FilterGroup__c": 2,
        "%vlocity_namespace%__FilterOperator__c": "=",
        "%vlocity_namespace%__FilterValue__c": "Birthdate",
        "%vlocity_namespace%__InterfaceFieldAPIName__c": "Birthdate",
        "%vlocity_namespace%__InterfaceObjectLookupOrder__c": 1,
        "%vlocity_namespace%__InterfaceObjectName__c": "Contact",
        "%vlocity_namespace%__IsDisabled__c": false,
        "%vlocity_namespace%__IsRequiredForUpsert__c": false,
        "%vlocity_namespace%__MapId__c": "ParticipantSearchCustom2736",
        "%vlocity_namespace%__UpsertKey__c": false,
        "CurrencyIsoCode": "USD",
        "Name": "ParticipantSearch",
        "VlocityDataPackType": "SObject",
        "VlocityRecordSObjectType": "%vlocity_namespace%__DRMapItem__c"
    },
    {
        "%vlocity_namespace%__DomainObjectAPIName__c": "Formula",
        "%vlocity_namespace%__DomainObjectCreationOrder__c": 0,
        "%vlocity_namespace%__DomainObjectFieldAPIName__c": "Formula",
        "%vlocity_namespace%__FormulaOrder__c": 1,
        "%vlocity_namespace%__FormulaResultPath__c": "Participant:LastNameMatchScore",
        "%vlocity_namespace%__Formula__c": "IF(AND(ISNOTBLANK(LastName),(LastName == Participant:LastName)),100,0)",
        "%vlocity_namespace%__IsDisabled__c": false,
        "%vlocity_namespace%__IsRequiredForUpsert__c": false,
        "%vlocity_namespace%__MapId__c": "ParticipantSearchCustom495",
        "%vlocity_namespace%__UpsertKey__c": false,
        "CurrencyIsoCode": "USD",
        "Name": "ParticipantSearch",
        "VlocityDataPackType": "SObject",
        "VlocityRecordSObjectType": "%vlocity_namespace%__DRMapItem__c"
    },
    {
        "%vlocity_namespace%__DomainObjectAPIName__c": "Formula",
        "%vlocity_namespace%__DomainObjectCreationOrder__c": 0,
        "%vlocity_namespace%__DomainObjectFieldAPIName__c": "Formula",
        "%vlocity_namespace%__FormulaOrder__c": 2,
        "%vlocity_namespace%__FormulaResultPath__c": "Participant:FirstNameMatchScore",
        "%vlocity_namespace%__Formula__c": "IF(AND(ISNOTBLANK(FirstName),(FirstName == Participant:FirstName)),100,0)",
        "%vlocity_namespace%__IsDisabled__c": false,
        "%vlocity_namespace%__IsRequiredForUpsert__c": false,
        "%vlocity_namespace%__MapId__c": "ParticipantSearchCustom5155",
        "%vlocity_namespace%__UpsertKey__c": false,
        "CurrencyIsoCode": "USD",
        "Name": "ParticipantSearch",
        "VlocityDataPackType": "SObject",
        "VlocityRecordSObjectType": "%vlocity_namespace%__DRMapItem__c"
    },
    {
        "%vlocity_namespace%__DomainObjectAPIName__c": "Formula",
        "%vlocity_namespace%__DomainObjectCreationOrder__c": 0,
        "%vlocity_namespace%__DomainObjectFieldAPIName__c": "Formula",
        "%vlocity_namespace%__FormulaOrder__c": 3,
        "%vlocity_namespace%__FormulaResultPath__c": "Participant:BirthdateDiff",
        "%vlocity_namespace%__Formula__c": "IF(AND(ISNOTBLANK(Birthdate),ISNOTBLANK(Participant:Birthdate)),DATEDIFF(Birthdate,Participant:Birthdate),100),0)",
        "%vlocity_namespace%__IsDisabled__c": false,
        "%vlocity_namespace%__IsRequiredForUpsert__c": false,
        "%vlocity_namespace%__MapId__c": "ParticipantSearchCustom611",
        "%vlocity_namespace%__UpsertKey__c": false,
        "CurrencyIsoCode": "USD",
        "Name": "ParticipantSearch",
        "VlocityDataPackType": "SObject",
        "VlocityRecordSObjectType": "%vlocity_namespace%__DRMapItem__c"
    },
    {
        "%vlocity_namespace%__DomainObjectAPIName__c": "Formula",
        "%vlocity_namespace%__DomainObjectCreationOrder__c": 0,
        "%vlocity_namespace%__DomainObjectFieldAPIName__c": "Formula",
        "%vlocity_namespace%__FormulaOrder__c": 4,
        "%vlocity_namespace%__FormulaResultPath__c": "Participant:BirthdateMatchScore",
        "%vlocity_namespace%__Formula__c": "100-MIN(ABS(Participant:BirthdateDiff),100)",
        "%vlocity_namespace%__IsDisabled__c": false,
        "%vlocity_namespace%__IsRequiredForUpsert__c": false,
        "%vlocity_namespace%__MapId__c": "ParticipantSearchCustom4472",
        "%vlocity_namespace%__UpsertKey__c": false,
        "CurrencyIsoCode": "USD",
        "Name": "ParticipantSearch",
        "VlocityDataPackType": "SObject",
        "VlocityRecordSObjectType": "%vlocity_namespace%__DRMapItem__c"
    },
    {
        "%vlocity_namespace%__DomainObjectAPIName__c": "Formula",
        "%vlocity_namespace%__DomainObjectCreationOrder__c": 0,
        "%vlocity_namespace%__DomainObjectFieldAPIName__c": "Formula",
        "%vlocity_namespace%__FormulaOrder__c": 5,
        "%vlocity_namespace%__FormulaResultPath__c": "Participant:MailingAddress",
        "%vlocity_namespace%__Formula__c": "CONCAT(Participant:MailingStreet,\" \",Participant:MailingCity,\" \",Participant:MailingState,\" \",Participant:MailingPostalCode)",
        "%vlocity_namespace%__IsDisabled__c": false,
        "%vlocity_namespace%__IsRequiredForUpsert__c": false,
        "%vlocity_namespace%__MapId__c": "ParticipantSearchCustom5847",
        "%vlocity_namespace%__UpsertKey__c": false,
        "CurrencyIsoCode": "USD",
        "Name": "ParticipantSearch",
        "VlocityDataPackType": "SObject",
        "VlocityRecordSObjectType": "%vlocity_namespace%__DRMapItem__c"
    },
    {
        "%vlocity_namespace%__DomainObjectAPIName__c": "Formula",
        "%vlocity_namespace%__DomainObjectCreationOrder__c": 0,
        "%vlocity_namespace%__DomainObjectFieldAPIName__c": "Formula",
        "%vlocity_namespace%__FormulaOrder__c": 6,
        "%vlocity_namespace%__FormulaResultPath__c": "Participant:TotalMatchScore",
        "%vlocity_namespace%__Formula__c": "ROUND(SUM(Participant:LastNameMatchScore,Participant:FirstNameMatchScore,Participant:BirthdateMatchScore) / 3,2)",
        "%vlocity_namespace%__IsDisabled__c": false,
        "%vlocity_namespace%__IsRequiredForUpsert__c": false,
        "%vlocity_namespace%__MapId__c": "ParticipantSearchCustom8568",
        "%vlocity_namespace%__UpsertKey__c": false,
        "CurrencyIsoCode": "USD",
        "Name": "ParticipantSearch",
        "VlocityDataPackType": "SObject",
        "VlocityRecordSObjectType": "%vlocity_namespace%__DRMapItem__c"
    },
    {
        "%vlocity_namespace%__DomainObjectAPIName__c": "Formula",
        "%vlocity_namespace%__DomainObjectCreationOrder__c": 0,
        "%vlocity_namespace%__DomainObjectFieldAPIName__c": "Formula",
        "%vlocity_namespace%__FormulaOrder__c": 7,
        "%vlocity_namespace%__FormulaResultPath__c": "Participant:Count",
        "%vlocity_namespace%__Formula__c": "IF(ISNOTBLANK(Participant:TotalMatchScore),1)",
        "%vlocity_namespace%__IsDisabled__c": false,
        "%vlocity_namespace%__IsRequiredForUpsert__c": false,
        "%vlocity_namespace%__MapId__c": "ParticipantSearchCustom215",
        "%vlocity_namespace%__UpsertKey__c": false,
        "CurrencyIsoCode": "USD",
        "Name": "ParticipantSearch",
        "VlocityDataPackType": "SObject",
        "VlocityRecordSObjectType": "%vlocity_namespace%__DRMapItem__c"
    },
    {
        "%vlocity_namespace%__DomainObjectAPIName__c": "Formula",
        "%vlocity_namespace%__DomainObjectCreationOrder__c": 0,
        "%vlocity_namespace%__DomainObjectFieldAPIName__c": "Formula",
        "%vlocity_namespace%__FormulaOrder__c": 8,
        "%vlocity_namespace%__FormulaResultPath__c": "SearchResultCount",
        "%vlocity_namespace%__Formula__c": "IF(ISNOTBLANK(Participant|1:LastName),SUM(Participant:Count),0)",
        "%vlocity_namespace%__IsDisabled__c": false,
        "%vlocity_namespace%__IsRequiredForUpsert__c": false,
        "%vlocity_namespace%__MapId__c": "ParticipantSearchCustom5095",
        "%vlocity_namespace%__UpsertKey__c": false,
        "CurrencyIsoCode": "USD",
        "Name": "ParticipantSearch",
        "VlocityDataPackType": "SObject",
        "VlocityRecordSObjectType": "%vlocity_namespace%__DRMapItem__c"
    },
    {
        "%vlocity_namespace%__DomainObjectAPIName__c": "json",
        "%vlocity_namespace%__DomainObjectCreationOrder__c": 1,
        "%vlocity_namespace%__DomainObjectFieldAPIName__c": "Participant:Birthdate",
        "%vlocity_namespace%__InterfaceFieldAPIName__c": "Participant:Birthdate",
        "%vlocity_namespace%__IsDisabled__c": false,
        "%vlocity_namespace%__IsRequiredForUpsert__c": false,
        "%vlocity_namespace%__MapId__c": "ParticipantSearchCustom1293",
        "%vlocity_namespace%__UpsertKey__c": false,
        "CurrencyIsoCode": "USD",
        "Name": "ParticipantSearch",
        "VlocityDataPackType": "SObject",
        "VlocityRecordSObjectType": "%vlocity_namespace%__DRMapItem__c"
    },
    {
        "%vlocity_namespace%__DomainObjectAPIName__c": "json",
        "%vlocity_namespace%__DomainObjectCreationOrder__c": 1,
        "%vlocity_namespace%__DomainObjectFieldAPIName__c": "Participant:BirthdateMatchScore",
        "%vlocity_namespace%__InterfaceFieldAPIName__c": "Participant:BirthdateMatchScore",
        "%vlocity_namespace%__IsDisabled__c": false,
        "%vlocity_namespace%__IsRequiredForUpsert__c": false,
        "%vlocity_namespace%__MapId__c": "ParticipantSearchCustom8384",
        "%vlocity_namespace%__UpsertKey__c": false,
        "CurrencyIsoCode": "USD",
        "Name": "ParticipantSearch",
        "VlocityDataPackType": "SObject",
        "VlocityRecordSObjectType": "%vlocity_namespace%__DRMapItem__c"
    },
    {
        "%vlocity_namespace%__DomainObjectAPIName__c": "json",
        "%vlocity_namespace%__DomainObjectCreationOrder__c": 1,
        "%vlocity_namespace%__DomainObjectFieldAPIName__c": "Participant:Email",
        "%vlocity_namespace%__InterfaceFieldAPIName__c": "Participant:Email",
        "%vlocity_namespace%__IsDisabled__c": false,
        "%vlocity_namespace%__IsRequiredForUpsert__c": false,
        "%vlocity_namespace%__MapId__c": "ParticipantSearchCustom3891",
        "%vlocity_namespace%__UpsertKey__c": false,
        "CurrencyIsoCode": "USD",
        "Name": "ParticipantSearch",
        "VlocityDataPackType": "SObject",
        "VlocityRecordSObjectType": "%vlocity_namespace%__DRMapItem__c"
    },
    {
        "%vlocity_namespace%__DomainObjectAPIName__c": "json",
        "%vlocity_namespace%__DomainObjectCreationOrder__c": 1,
        "%vlocity_namespace%__DomainObjectFieldAPIName__c": "Participant:FirstName",
        "%vlocity_namespace%__InterfaceFieldAPIName__c": "Participant:FirstName",
        "%vlocity_namespace%__IsDisabled__c": false,
        "%vlocity_namespace%__IsRequiredForUpsert__c": false,
        "%vlocity_namespace%__MapId__c": "ParticipantSearchCustom3802",
        "%vlocity_namespace%__UpsertKey__c": false,
        "CurrencyIsoCode": "USD",
        "Name": "ParticipantSearch",
        "VlocityDataPackType": "SObject",
        "VlocityRecordSObjectType": "%vlocity_namespace%__DRMapItem__c"
    },
    {
        "%vlocity_namespace%__DomainObjectAPIName__c": "json",
        "%vlocity_namespace%__DomainObjectCreationOrder__c": 1,
        "%vlocity_namespace%__DomainObjectFieldAPIName__c": "Participant:FirstNameMatchScore",
        "%vlocity_namespace%__InterfaceFieldAPIName__c": "Participant:FirstNameMatchScore",
        "%vlocity_namespace%__IsDisabled__c": false,
        "%vlocity_namespace%__IsRequiredForUpsert__c": false,
        "%vlocity_namespace%__MapId__c": "ParticipantSearchCustom1873",
        "%vlocity_namespace%__UpsertKey__c": false,
        "CurrencyIsoCode": "USD",
        "Name": "ParticipantSearch",
        "VlocityDataPackType": "SObject",
        "VlocityRecordSObjectType": "%vlocity_namespace%__DRMapItem__c"
    },
    {
        "%vlocity_namespace%__DomainObjectAPIName__c": "json",
        "%vlocity_namespace%__DomainObjectCreationOrder__c": 1,
        "%vlocity_namespace%__DomainObjectFieldAPIName__c": "Participant:Id",
        "%vlocity_namespace%__InterfaceFieldAPIName__c": "Participant:Id",
        "%vlocity_namespace%__IsDisabled__c": false,
        "%vlocity_namespace%__IsRequiredForUpsert__c": false,
        "%vlocity_namespace%__MapId__c": "ParticipantSearchCustom2592",
        "%vlocity_namespace%__UpsertKey__c": false,
        "CurrencyIsoCode": "USD",
        "Name": "ParticipantSearch",
        "VlocityDataPackType": "SObject",
        "VlocityRecordSObjectType": "%vlocity_namespace%__DRMapItem__c"
    },
    {
        "%vlocity_namespace%__DomainObjectAPIName__c": "json",
        "%vlocity_namespace%__DomainObjectCreationOrder__c": 1,
        "%vlocity_namespace%__DomainObjectFieldAPIName__c": "Participant:LastName",
        "%vlocity_namespace%__InterfaceFieldAPIName__c": "Participant:LastName",
        "%vlocity_namespace%__IsDisabled__c": false,
        "%vlocity_namespace%__IsRequiredForUpsert__c": false,
        "%vlocity_namespace%__MapId__c": "ParticipantSearchCustom8081",
        "%vlocity_namespace%__UpsertKey__c": false,
        "CurrencyIsoCode": "USD",
        "Name": "ParticipantSearch",
        "VlocityDataPackType": "SObject",
        "VlocityRecordSObjectType": "%vlocity_namespace%__DRMapItem__c"
    },
    {
        "%vlocity_namespace%__DomainObjectAPIName__c": "json",
        "%vlocity_namespace%__DomainObjectCreationOrder__c": 1,
        "%vlocity_namespace%__DomainObjectFieldAPIName__c": "Participant:LastNameMatchScore",
        "%vlocity_namespace%__InterfaceFieldAPIName__c": "Participant:LastNameMatchScore",
        "%vlocity_namespace%__IsDisabled__c": false,
        "%vlocity_namespace%__IsRequiredForUpsert__c": false,
        "%vlocity_namespace%__MapId__c": "ParticipantSearchCustom6898",
        "%vlocity_namespace%__UpsertKey__c": false,
        "CurrencyIsoCode": "USD",
        "Name": "ParticipantSearch",
        "VlocityDataPackType": "SObject",
        "VlocityRecordSObjectType": "%vlocity_namespace%__DRMapItem__c"
    },
    {
        "%vlocity_namespace%__DomainObjectAPIName__c": "json",
        "%vlocity_namespace%__DomainObjectCreationOrder__c": 1,
        "%vlocity_namespace%__DomainObjectFieldAPIName__c": "Participant:MailingAddress",
        "%vlocity_namespace%__InterfaceFieldAPIName__c": "Participant:MailingAddress",
        "%vlocity_namespace%__IsDisabled__c": false,
        "%vlocity_namespace%__IsRequiredForUpsert__c": false,
        "%vlocity_namespace%__MapId__c": "ParticipantSearchCustom1936",
        "%vlocity_namespace%__UpsertKey__c": false,
        "CurrencyIsoCode": "USD",
        "Name": "ParticipantSearch",
        "VlocityDataPackType": "SObject",
        "VlocityRecordSObjectType": "%vlocity_namespace%__DRMapItem__c"
    },
    {
        "%vlocity_namespace%__DomainObjectAPIName__c": "json",
        "%vlocity_namespace%__DomainObjectCreationOrder__c": 1,
        "%vlocity_namespace%__DomainObjectFieldAPIName__c": "Participant:MailingCity",
        "%vlocity_namespace%__InterfaceFieldAPIName__c": "Participant:MailingCity",
        "%vlocity_namespace%__IsDisabled__c": false,
        "%vlocity_namespace%__IsRequiredForUpsert__c": false,
        "%vlocity_namespace%__MapId__c": "ParticipantSearchCustom2096",
        "%vlocity_namespace%__UpsertKey__c": false,
        "CurrencyIsoCode": "USD",
        "Name": "ParticipantSearch",
        "VlocityDataPackType": "SObject",
        "VlocityRecordSObjectType": "%vlocity_namespace%__DRMapItem__c"
    },
    {
        "%vlocity_namespace%__DomainObjectAPIName__c": "json",
        "%vlocity_namespace%__DomainObjectCreationOrder__c": 1,
        "%vlocity_namespace%__DomainObjectFieldAPIName__c": "Participant:MailingPostalCode",
        "%vlocity_namespace%__InterfaceFieldAPIName__c": "Participant:MailingPostalCode",
        "%vlocity_namespace%__IsDisabled__c": false,
        "%vlocity_namespace%__IsRequiredForUpsert__c": false,
        "%vlocity_namespace%__MapId__c": "ParticipantSearchCustom3787",
        "%vlocity_namespace%__UpsertKey__c": false,
        "CurrencyIsoCode": "USD",
        "Name": "ParticipantSearch",
        "VlocityDataPackType": "SObject",
        "VlocityRecordSObjectType": "%vlocity_namespace%__DRMapItem__c"
    },
    {
        "%vlocity_namespace%__DomainObjectAPIName__c": "json",
        "%vlocity_namespace%__DomainObjectCreationOrder__c": 1,
        "%vlocity_namespace%__DomainObjectFieldAPIName__c": "Participant:MailingState",
        "%vlocity_namespace%__InterfaceFieldAPIName__c": "Participant:MailingState",
        "%vlocity_namespace%__IsDisabled__c": false,
        "%vlocity_namespace%__IsRequiredForUpsert__c": false,
        "%vlocity_namespace%__MapId__c": "ParticipantSearchCustom3867",
        "%vlocity_namespace%__UpsertKey__c": false,
        "CurrencyIsoCode": "USD",
        "Name": "ParticipantSearch",
        "VlocityDataPackType": "SObject",
        "VlocityRecordSObjectType": "%vlocity_namespace%__DRMapItem__c"
    },
    {
        "%vlocity_namespace%__DomainObjectAPIName__c": "json",
        "%vlocity_namespace%__DomainObjectCreationOrder__c": 1,
        "%vlocity_namespace%__DomainObjectFieldAPIName__c": "Participant:MailingStreet",
        "%vlocity_namespace%__InterfaceFieldAPIName__c": "Participant:MailingStreet",
        "%vlocity_namespace%__IsDisabled__c": false,
        "%vlocity_namespace%__IsRequiredForUpsert__c": false,
        "%vlocity_namespace%__MapId__c": "ParticipantSearchCustom3316",
        "%vlocity_namespace%__UpsertKey__c": false,
        "CurrencyIsoCode": "USD",
        "Name": "ParticipantSearch",
        "VlocityDataPackType": "SObject",
        "VlocityRecordSObjectType": "%vlocity_namespace%__DRMapItem__c"
    },
    {
        "%vlocity_namespace%__DomainObjectAPIName__c": "json",
        "%vlocity_namespace%__DomainObjectCreationOrder__c": 1,
        "%vlocity_namespace%__DomainObjectFieldAPIName__c": "Participant:PartyId",
        "%vlocity_namespace%__InterfaceFieldAPIName__c": "Participant:%vlocity_namespace%__PartyId__c",
        "%vlocity_namespace%__IsDisabled__c": false,
        "%vlocity_namespace%__IsRequiredForUpsert__c": false,
        "%vlocity_namespace%__MapId__c": "ParticipantSearchCustom2331",
        "%vlocity_namespace%__UpsertKey__c": false,
        "CurrencyIsoCode": "USD",
        "Name": "ParticipantSearch",
        "VlocityDataPackType": "SObject",
        "VlocityRecordSObjectType": "%vlocity_namespace%__DRMapItem__c"
    },
    {
        "%vlocity_namespace%__DomainObjectAPIName__c": "json",
        "%vlocity_namespace%__DomainObjectCreationOrder__c": 1,
        "%vlocity_namespace%__DomainObjectFieldAPIName__c": "Participant:SocialSecurityNumber",
        "%vlocity_namespace%__InterfaceFieldAPIName__c": "Participant:%vlocity_namespace%__SocialSecurityNumber__c",
        "%vlocity_namespace%__IsDisabled__c": false,
        "%vlocity_namespace%__IsRequiredForUpsert__c": false,
        "%vlocity_namespace%__MapId__c": "ParticipantSearchCustom1087",
        "%vlocity_namespace%__UpsertKey__c": false,
        "CurrencyIsoCode": "USD",
        "Name": "ParticipantSearch",
        "VlocityDataPackType": "SObject",
        "VlocityRecordSObjectType": "%vlocity_namespace%__DRMapItem__c"
    },
    {
        "%vlocity_namespace%__DomainObjectAPIName__c": "json",
        "%vlocity_namespace%__DomainObjectCreationOrder__c": 1,
        "%vlocity_namespace%__DomainObjectFieldAPIName__c": "Participant:TotalMatchScore",
        "%vlocity_namespace%__InterfaceFieldAPIName__c": "Participant:TotalMatchScore",
        "%vlocity_namespace%__IsDisabled__c": false,
        "%vlocity_namespace%__IsRequiredForUpsert__c": false,
        "%vlocity_namespace%__MapId__c": "ParticipantSearchCustom5317",
        "%vlocity_namespace%__UpsertKey__c": false,
        "CurrencyIsoCode": "USD",
        "Name": "ParticipantSearch",
        "VlocityDataPackType": "SObject",
        "VlocityRecordSObjectType": "%vlocity_namespace%__DRMapItem__c"
    },
    {
        "%vlocity_namespace%__DomainObjectAPIName__c": "json",
        "%vlocity_namespace%__DomainObjectCreationOrder__c": 1,
        "%vlocity_namespace%__DomainObjectFieldAPIName__c": "SearchResultCount",
        "%vlocity_namespace%__InterfaceFieldAPIName__c": "SearchResultCount",
        "%vlocity_namespace%__IsDisabled__c": false,
        "%vlocity_namespace%__IsRequiredForUpsert__c": false,
        "%vlocity_namespace%__MapId__c": "ParticipantSearchCustom7137",
        "%vlocity_namespace%__UpsertKey__c": false,
        "CurrencyIsoCode": "USD",
        "Name": "ParticipantSearch",
        "VlocityDataPackType": "SObject",
        "VlocityRecordSObjectType": "%vlocity_namespace%__DRMapItem__c"
    }
]