{
    "ContextId": "a0M6g000002hbhQEAQ",
    "OutcomePartyName": [
        "Andrea Rousy",
        "Samuel Rousy"
    ],
    "ServicePlanDetails": {
        "ObjectiveDescription": "This is my objective",
        "ParticipantName-Block": {
            "ParticipantName": "Samuel Rousy"
        },
        "PlanObjective": "This is my objective",
        "StartDate": "2020-02-01",
        "Status": "In Progress",
        "TargetCompletionDate": "2020-02-01"
    },
    "id": "a2H6g000000iMcBEAU",
    "isdtp": "p1",
    "layout": "lightning",
    "sfdcIFrameHost": "web",
    "sfdcIFrameOrigin": "https://jb-vko2020--vlocity-ps.visualforce.com",
    "timeStamp": "2020-02-19T18:37:44.159Z",
    "userCurrencyCode": "USD",
    "userId": "0056g000003NOAyAAO",
    "userName": "jblankenship@jb-vko2020.demo",
    "userProfile": "System Administrator",
    "userTimeZone": -480,
    "vlcPersistentComponent": {
    }
}