{
    "%vlocity_namespace%__Active__c": true,
    "%vlocity_namespace%__OmniScriptId__c": {
        "Name": "VPLXXX-ChildWelfareResponseScreen",
        "VlocityDataPackType": "VlocityMatchingKeyObject",
        "VlocityMatchingRecordSourceKey": "%vlocity_namespace%__OmniScript__c/VPLXXX/MandatoryReporter/English",
        "VlocityRecordSObjectType": "%vlocity_namespace%__OmniScript__c"
    },
    "%vlocity_namespace%__ParentElementId__c": {
        "%vlocity_namespace%__OmniScriptId__c": {
            "Name": "VPLXXX-ChildWelfareResponseScreen",
            "VlocityDataPackType": "VlocityMatchingKeyObject",
            "VlocityMatchingRecordSourceKey": "%vlocity_namespace%__OmniScript__c/VPLXXX/MandatoryReporter/English",
            "VlocityRecordSObjectType": "%vlocity_namespace%__OmniScript__c"
        },
        "Name": "EmotionalAbuseTreeScoreBlock",
        "VlocityDataPackType": "VlocityMatchingKeyObject",
        "VlocityMatchingRecordSourceKey": "%vlocity_namespace%__Element__c/%vlocity_namespace%__OmniScript__c/VPLXXX/MandatoryReporter/English/EmotionalAbuseTreeScoreBlock",
        "VlocityRecordSObjectType": "%vlocity_namespace%__Element__c"
    },
    "%vlocity_namespace%__ParentElementName__c": "EmotionalAbuseTreeScoreBlock",
    "%vlocity_namespace%__ParentElementType__c": "Block",
    "%vlocity_namespace%__PropertySet__c": {
        "HTMLTemplateId": "",
        "controlWidth": 12,
        "dataType": "Text",
        "dateFormat": "MM-dd-yyyy",
        "disOnTplt": false,
        "expression": "IF(OR(%ChildExhibitingBehavior%=\"Yes\",%CaregiversBehaviorCruelBizarreDangerous%=\"Yes\"), \"Within 24 Hours\",\"Within 10 Days\")",
        "hide": true,
        "hideGroupSep": false,
        "inputWidth": 12,
        "label": "Formula4",
        "mask": null,
        "show": null,
        "showInputWidth": false
    },
    "%vlocity_namespace%__ReusableOmniScript__c": true,
    "%vlocity_namespace%__Type__c": "Formula",
    "CurrencyIsoCode": "USD",
    "Name": "EmotionalAbuseTreeScoreFormula",
    "VlocityDataPackType": "SObject",
    "VlocityRecordSObjectType": "%vlocity_namespace%__Element__c",
    "VlocityRecordSourceKey": "%vlocity_namespace%__Element__c/%vlocity_namespace%__OmniScript__c/VPLXXX/MandatoryReporter/English/EmotionalAbuseTreeScoreFormula"
}